<?xml version="1.0" encoding="UTF-8"?>
<plist version="1.0">
<array>
	<dict>
		<key>shortcutsFileName</key>
		<string>PS</string>
		<key>softwareName</key>
		<string>PS</string>
	</dict>
	<dict>
		<key>shortcutsFileName</key>
		<string>AI</string>
		<key>softwareName</key>
		<string>AI</string>
	</dict>
	<dict>
		<key>shortcutsFileName</key>
		<string>CAD</string>
		<key>softwareName</key>
		<string>CAD</string>
	</dict>
	<dict>
		<key>shortcutsFileName</key>
		<string>3Dmax</string>
		<key>softwareName</key>
		<string>3Dmax</string>
	</dict>
	<dict>
		<key>shortcutsFileName</key>
		<string>AE</string>
		<key>softwareName</key>
		<string>AE</string>
	</dict>
	<dict>
		<key>shortcutsFileName</key>
		<string>CDR</string>
		<key>softwareName</key>
		<string>CDR</string>
	</dict>
	<dict>
		<key>shortcutsFileName</key>
		<string>DW</string>
		<key>softwareName</key>
		<string>DW</string>
	</dict>
	<dict>
		<key>shortcutsFileName</key>
		<string>Flash</string>
		<key>softwareName</key>
		<string>Flash</string>
	</dict>
	<dict>
		<key>shortcutsFileName</key>
		<string>ID</string>
		<key>softwareName</key>
		<string>ID</string>
	</dict>
	<dict>
		<key>shortcutsFileName</key>
		<string>PR</string>
		<key>softwareName</key>
		<string>PR</string>
	</dict>
	<dict>
		<key>shortcutsFileName</key>
		<string>SU</string>
		<key>softwareName</key>
		<string>SU</string>
	</dict>
	<dict>
		<key>shortcutsFileName</key>
		<string>keyshot</string>
		<key>softwareName</key>
		<string>keyshot</string>
	</dict>
	<dict>
		<key>shortcutsFileName</key>
		<string>maya</string>
		<key>softwareName</key>
		<string>maya</string>
	</dict>
	<dict>
		<key>shortcutsFileName</key>
		<string>proE</string>
		<key>softwareName</key>
		<string>proE</string>
	</dict>
	<dict>
		<key>shortcutsFileName</key>
		<string>rhino</string>
		<key>softwareName</key>
		<string>rhino</string>
	</dict>
</array>
</plist>
